[
  {
    "id": 1,
    "send": false,
    "receive": true,
    "version": 0,
    "intent_id": 2,
    "widget_definition_id": 19
  },
  {
    "id": 2,
    "send": true,
    "receive": false,
    "version": 0,
    "intent_id": 1,
    "widget_definition_id": 20
  },
  {
    "id": 3,
    "send": true,
    "receive": false,
    "version": 0,
    "intent_id": 2,
    "widget_definition_id": 20
  },
  {
    "id": 4,
    "send": false,
    "receive": true,
    "version": 0,
    "intent_id": 1,
    "widget_definition_id": 21
  }
]